cowin_api/__init__.py
cowin_api/api.py
cowin_api/base_api.py
cowin_api/constants.py
cowin_api/utils.py
cowin-0.0.4.dist-info/METADATA
cowin-0.0.4.dist-info/WHEEL
cowin-0.0.4.dist-info/top_level.txt
cowin-0.0.4.dist-info/RECORD
